spotipy/__init__.py
spotipy/_version.py
spotipy/hrnet.py
spotipy/model.py
spotipy/multiscalenet.py
spotipy/unetplus.py
spotipy/utils.py
spotipy_detector-0.1.0.dist-info/LICENSE
spotipy_detector-0.1.0.dist-info/METADATA
spotipy_detector-0.1.0.dist-info/WHEEL
spotipy_detector-0.1.0.dist-info/top_level.txt
spotipy_detector-0.1.0.dist-info/RECORD
